[
  {
    "timestamp": "19:30",
    "end_timestamp": "20:15",
    "quote": "We make good agents into great agents by focusing on their strengths and automating their weaknesses.",
    "clip_type": "tactical_specificity",
    "why_clipworthy": "It provides a clear strategy for agent development that is both actionable and inspiring.",
    "suggested_hook": "Want to turn your good agents into great ones? Here's how Ryan Rodenbeck does it."
  },
  {
    "timestamp": "28:30",
    "end_timestamp": "29:15",
    "quote": "The reality is that commissions might go down, but with the right approach, you can still thrive.",
    "clip_type": "mindset_shift",
    "why_clipworthy": "Addresses a common fear with a positive outlook and actionable advice.",
    "suggested_hook": "Worried about commission changes? Here's why you shouldn't be."
  }
]