[
  {
    "timestamp": "00:04:49",
    "end_timestamp": "00:05:55",
    "quote": "Imagine AI scheduling showings and negotiating contracts for you.",
    "clip_type": "pattern_reveal",
    "why_clipworthy": "Illustrates a future where AI handles complex tasks, sparking curiosity.",
    "suggested_hook": "Is AI the future of real estate transactions?"
  },
  {
    "timestamp": "00:19:06",
    "end_timestamp": "00:19:49",
    "quote": "50% of agents not using AI will disappear.",
    "clip_type": "contrarian_take",
    "why_clipworthy": "Challenges agents to adopt AI or risk obsolescence.",
    "suggested_hook": "Why ignoring AI could end your real estate career."
  }
]