[
  {
    "timestamp": "14:00",
    "end_timestamp": "15:00",
    "quote": "The real problem lately is motivation, not inventory.",
    "clip_type": "contrarian_take",
    "why_clipworthy": "Challenges the common belief that inventory is the main issue.",
    "suggested_hook": "Think inventory is the biggest issue in real estate? Think again."
  },
  {
    "timestamp": "39:00",
    "end_timestamp": "40:00",
    "quote": "Every home I sell, I want to be the beginning of a long-term relationship.",
    "clip_type": "emotional_resonance",
    "why_clipworthy": "Highlights the importance of relationship-building in real estate.",
    "suggested_hook": "Why every transaction should be the start of a lifelong relationship."
  }
]