[
  {
    "timestamp": "07:00",
    "end_timestamp": "07:45",
    "quote": "The greatest moments of growth occur when you're being challenged the most.",
    "clip_type": "mindset_shift",
    "why_clipworthy": "This quote encapsulates the essence of resilience and turning challenges into opportunities.",
    "suggested_hook": "Discover how challenges can be your greatest growth opportunities."
  },
  {
    "timestamp": "38:00",
    "end_timestamp": "38:45",
    "quote": "Life isn't an adventure unless there's a U-turn or two or ten.",
    "clip_type": "memorable_oneliner",
    "why_clipworthy": "A memorable line that highlights the unpredictability of life and the need to adapt.",
    "suggested_hook": "Embrace the unexpected turns in your real estate journey."
  }
]