[
  {
    "timestamp": "05:05",
    "end_timestamp": "06:33",
    "quote": "Auto real app takes static images and turns them into viral video... It brings it to life.",
    "clip_type": "tactical_specificity",
    "why_clipworthy": "Demonstrates a specific AI tool that can enhance real estate marketing.",
    "suggested_hook": "Transform your real estate photos into captivating videos with this AI tool!"
  },
  {
    "timestamp": "36:00",
    "end_timestamp": "37:10",
    "quote": "If you're renting, we know that's 100% loss... owning a home improves culture, society, civilization writ large.",
    "clip_type": "mindset_shift",
    "why_clipworthy": "Challenges the notion that renting is a better financial decision than owning.",
    "suggested_hook": "Why renting might be costing you more than you think!"
  }
]