[
  {
    "timestamp": "00:04:24",
    "end_timestamp": "00:05:09",
    "quote": "Stop trying to do everything yourself. Once I started delegating away and really structuring my business with processes and people, my business just grew and stress went down.",
    "clip_type": "mindset_shift",
    "why_clipworthy": "It challenges the hustle culture by emphasizing smarter work over harder work.",
    "suggested_hook": "Are you still trying to do everything yourself in real estate?"
  },
  {
    "timestamp": "00:09:01",
    "end_timestamp": "00:09:23",
    "quote": "YouTube does favor older content if it's good and that stuff just lives forever and you can continually get leads.",
    "clip_type": "tactical_specificity",
    "why_clipworthy": "Highlights the long-term value of creating quality content on YouTube.",
    "suggested_hook": "Why YouTube should be your secret weapon for real estate marketing."
  }
]